better_gradient/__init__.py
better_gradient/better_gradient.py
better_gradient-0.3.0.dist-info/LICENSE
better_gradient-0.3.0.dist-info/METADATA
better_gradient-0.3.0.dist-info/WHEEL
better_gradient-0.3.0.dist-info/entry_points.txt
better_gradient-0.3.0.dist-info/top_level.txt
better_gradient-0.3.0.dist-info/RECORD
