Metadata-Version: 2.1
Name: better_gradient
Version: 0.3.0
Summary: A package to print gradients with terminal colors
Home-page: https://github.com/OGZhu/better_gradient
Author: OGZhu
Author-email: OGZhu@lol.com
Classifier: Programming Language :: Python :: 3
Classifier: License :: OSI Approved :: MIT License
Classifier: Operating System :: OS Independent
Requires-Python: >=3.6
License-File: LICENSE
Requires-Dist: requests
